rynaki/__init__.py
rynaki/main.py
rynaki-0.1.3.dist-info/METADATA
rynaki-0.1.3.dist-info/WHEEL
rynaki-0.1.3.dist-info/top_level.txt
rynaki-0.1.3.dist-info/RECORD
